foxops_client/__init__.py
foxops_client/client_async.py
foxops_client/client_sync.py
foxops_client/exceptions.py
foxops_client/py.typed
foxops_client/retries.py
foxops_client/types.py
foxops_client-0.4.0.dist-info/METADATA
foxops_client-0.4.0.dist-info/WHEEL
foxops_client-0.4.0.dist-info/licenses/LICENSE
foxops_client-0.4.0.dist-info/RECORD
