Metadata-Version: 2.4
Name: foxops-client
Version: 0.4.0
Summary: Foxops API Client
License-File: LICENSE
Author: Alexander Hungenberg
Author-email: alexander.hungenberg@roche.com
Requires-Python: >=3.13,<3.14
Classifier: Programming Language :: Python :: 3
Classifier: Programming Language :: Python :: 3.13
Requires-Dist: httpx (>=0.28.1,<0.29.0)
Requires-Dist: structlog (>=23.1.0,<24.0.0)
Requires-Dist: tenacity (>=9.1.2,<10.0.0)
